tests/helpers/__init__.py
tests/helpers/cuda_check.py
time_series_models/__init__.py
time_series_models/lstm.py
time_series_models/quantum_lstm.py
time_series_models-0.3.9.dist-info/LICENSE
time_series_models-0.3.9.dist-info/METADATA
time_series_models-0.3.9.dist-info/WHEEL
time_series_models-0.3.9.dist-info/top_level.txt
time_series_models-0.3.9.dist-info/RECORD
