Metadata-Version: 2.1
Name: time-series-models
Version: 0.3.9
Summary: Neural netork models for time-series-predictor.
Home-page: https://github.com/krypton-unite/time_series_models.git
Author: Daniel Kaminski de Souza
Author-email: daniel@kryptonunite.com
License: The Unlicense
Download-URL: https://pypi.org/project/time-series-models/
Keywords: Time series models
Platform: UNKNOWN
Requires-Dist: pennylane
Requires-Dist: torch
Provides-Extra: dev
Requires-Dist: autopep8 ; extra == 'dev'
Requires-Dist: bumpversion ; extra == 'dev'
Requires-Dist: twine ; extra == 'dev'
Requires-Dist: wheel ; extra == 'dev'
Provides-Extra: test
Requires-Dist: flights-time-series-dataset ; extra == 'test'
Requires-Dist: pytest ; extra == 'test'
Requires-Dist: pytest-cov ; extra == 'test'
Requires-Dist: time-series-predictor ; extra == 'test'
